{
    "1000": "bi-sun",
    "1003": "bi-cloud-sun",
    "1006": "bi-cloud",
    "1009": "bi-cloudy",
    "1030": "bi-cloud-haze",
    "1063": "bi-cloud-drizzle",
    "1066": "bi-cloud-sleet",
    "1069": "bi-cloud-snow",
    "1072": "bi-cloud-sleet",
    "1114": "bi-cloud-snow",
    "1117": "bi-cloud-hail",
    "1135": "bi-cloud-fog",
    "1147": "bi-cloud-haze",
    "1150": "bi-cloud-drizzle",
    "1153": "bi-cloud-sleet",
    "1168": "bi-cloud-snow",
    "1171": "bi-cloud-hail",
    "1180": "bi-cloud-drizzle",
    "1183": "bi-cloud-drizzle",
    "1186": "bi-cloud-lightning-rain",
    "1189": "bi-cloud-lightning-rain",
    "1192": "bi-cloud-lightning-rain",
    "1195": "bi-cloud-lightning-rain",
    "1198": "bi-cloud-lightning",
    "1201": "bi-cloud-lightning",
    "1204": "bi-cloud-lightning",
    "1207": "bi-cloud-lightning",
    "1210": "bi-cloud-lightning",
    "1213": "bi-cloud-lightning",
    "1216": "bi-cloud-snow",
    "1219": "bi-cloud-snow",
    "1222": "bi-cloud-snow",
    "1225": "bi-cloud-snow",
    "1237": "bi-cloud-snow",
    "1240": "bi-cloud-snow",
    "1243": "bi-cloud-snow",
    "1246": "bi-cloud-snow",
    "1249": "bi-cloud-snow",
    "1252": "bi-cloud-snow",
    "1273": "bi-cloud-hail",
    "1276": "bi-cloud-hail",
    "1279": "bi-cloud-hail",
    "1282": "bi-cloud-hail",
    "1285": "bi-cloud-snow",
    "1288": "bi-cloud-snow",
    "1291": "bi-cloud-snow"
}
